MANIFEST.in
README.rst
setup.py
correlcalc/__init__.py
correlcalc/antpcf.py
correlcalc/comovdist.py
correlcalc/datprep.py
correlcalc/datvis.py
correlcalc/fileios.py
correlcalc/genrand.py
correlcalc/main.py
correlcalc/metrics.c
correlcalc/metrics.pyx
correlcalc/metrics.so
correlcalc/metricsetup.py
correlcalc/param.py
correlcalc/runtimeupdate.py
correlcalc/test.py
correlcalc/tpcf.py
correlcalc.egg-info/PKG-INFO
correlcalc.egg-info/SOURCES.txt
correlcalc.egg-info/dependency_links.txt
correlcalc.egg-info/not-zip-safe
correlcalc.egg-info/requires.txt
correlcalc.egg-info/top_level.txt
correlcalc/correlcalc/metrics.so