Metadata-Version: 1.0
Name: correlcalc
Version: 0.971rc6
Summary: Two-point correlation function (2pCF) calculation
Home-page: http://github.com/rohinkumar/correlcalc
Author: Rohin Kumar Y
Author-email: yrohinkumar@gmail.com
License: MIT
Platform: UNKNOWN
